LICENSE
MANIFEST.in
README.md
setup.py
bin/pyeupi
pyeupi/__init__.py
pyeupi/api.py
pyeupi.egg-info/PKG-INFO
pyeupi.egg-info/SOURCES.txt
pyeupi.egg-info/dependency_links.txt
pyeupi.egg-info/requires.txt
pyeupi.egg-info/top_level.txt