Metadata-Version: 1.1
Name: pyeupi
Version: 0.9
Summary: Python API for the European Union anti-phishing initiative.
Home-page: https://github.com/CIRCL/PyEUPI
Author: Raphaël Vinot
Author-email: raphael.vinot@circl.lu
License: UNKNOWN
Platform: UNKNOWN
Classifier: License :: OSI Approved :: BSD License
Classifier: Development Status :: 4 - Beta
Classifier: Environment :: Console
Classifier: Intended Audience :: Science/Research
Classifier: Intended Audience :: Telecommunications Industry
Classifier: Programming Language :: Python :: 2.7
Classifier: Programming Language :: Python :: 3
Classifier: Topic :: Security
Classifier: Topic :: Internet
